obj_hash/__init__.py
obj_hash/test.py
obj_hash-0.0.0.dist-info/METADATA
obj_hash-0.0.0.dist-info/WHEEL
obj_hash-0.0.0.dist-info/top_level.txt
obj_hash-0.0.0.dist-info/RECORD
